{
  "steps": [
    {
      "slug": "gender",
      "children": [
        {
          "name": "GenderForm",
          "title": "Wybierz swoją płeć",
          "buttons": [{
            "form_name" : "gender",
            "value": "female",
            "text": "Jestem Kobietą",
            "selected": true
          },{
            "form_name" : "gender",
            "value": "male",
            "text": "Jestem Mezczyzną",
            "selected": false
          }]
        }
      ],
      "next_step": "basic-info"
    },
    {
      "slug": "basic-info",
      "children": [
        {
          "name": "BasicInfoForm",
          "title": "No to zaczynamy!",
          "description" : "Na podstawie Twoich danych jesteśmy w stanie określić twoje zapotrzebowanie na różne składniki, określić dietę, itp.",
          "buttons": [{
            "form_name" : "age",
            "value": ["18","19","20","21","22","23"],
            "unit": "lat",
            "text": "Wiek",
            "selected": false
          },{
            "form_name" : "height",
            "value": ["170","175","180","185","190","195"],
            "unit": "cm",
            "text": "Wzrost",
            "selected": false
          },{
            "form_name" : "Weight",
            "value": ["50","55","60","65","70","75"],
            "unit": "kg",
            "text": "Waga",
            "selected": false
          }]
        }
      ],
      "next_step": "informacje-podstawowe"
    }
  ]
}
